pycon_gui/__init__.py
pycon_gui/arrow_menu.py
pycon_gui-0.0.1.dist-info/LICENSE
pycon_gui-0.0.1.dist-info/METADATA
pycon_gui-0.0.1.dist-info/WHEEL
pycon_gui-0.0.1.dist-info/top_level.txt
pycon_gui-0.0.1.dist-info/RECORD
